federhmaccard/__main__.py
federhmaccard/password_request_uri.py
federhmaccard/pubsub.py
federhmaccard/seed_to_password.py
federhmaccard/card_io/__init__.py
federhmaccard/card_io/crypto.py
federhmaccard/card_io/error.py
federhmaccard/card_io/observer.py
federhmaccard/card_io/vault.py
federhmaccard/card_io/commands/FC_GET_CHALLENGE.py
federhmaccard/card_io/commands/FC_VAULT_CLOSE.py
federhmaccard/card_io/commands/FC_VAULT_HMAC_SHA1.py
federhmaccard/card_io/commands/FC_VAULT_HMAC_SHA256.py
federhmaccard/card_io/commands/FC_VAULT_IMPORT.py
federhmaccard/card_io/commands/FC_VAULT_OPEN.py
federhmaccard/card_io/commands/FC_VAULT_REENCRYPT.py
federhmaccard/card_io/commands/FC_VAULT_STATUS.py
federhmaccard/card_io/commands/FC_VERIFY.py
federhmaccard/card_io/commands/_prototype.py
federhmaccard/gui/BinaryValueEntry.py
federhmaccard/gui/CustomizedLabelFrame.py
federhmaccard/gui/FrameCardUnlock.py
federhmaccard/gui/FrameVault.py
federhmaccard/gui/FrameVaultTabAdvanced.py
federhmaccard/gui/FrameVaultTabController.py
federhmaccard/gui/FrameVaultTabDecrypt.py
federhmaccard/gui/FrameVaultTabPasswordgen.py
federhmaccard/gui/FrameVaultTabTOTP.py
federhmaccard/gui/FrameVaultTabTreeview.py
federhmaccard/gui/FrameWaitCard.py
federhmaccard/gui/PasswordGen.py
federhmaccard/gui/PasswordResultDisplay.py
federhmaccard/gui/PasswordTreeview.py
federhmaccard/gui/ValueCheck.py
federhmaccard/gui/ValueEntry.py
federhmaccard/gui/VaultSelector.py
federhmaccard/gui/__init__.py
federhmaccard-1.0.dist-info/METADATA
federhmaccard-1.0.dist-info/WHEEL
federhmaccard-1.0.dist-info/top_level.txt
federhmaccard-1.0.dist-info/RECORD
