Metadata-Version: 2.1
Name: federhmaccard
Version: 1.0
Requires-Dist: pyperclip
Requires-Dist: pyscard
